archit_ug/__init__.py
archit_ug/cerebras_key.txt
archit_ug/core.py
archit_ug-0.4.5.dist-info/licenses/LICENSE
archit_ug-0.4.5.dist-info/METADATA
archit_ug-0.4.5.dist-info/WHEEL
archit_ug-0.4.5.dist-info/top_level.txt
archit_ug-0.4.5.dist-info/RECORD
