Metadata-Version: 2.4
Name: archit_ug
Version: 0.4.5
Summary: Errol 4 Sonic - 120B Formal Interactive AI Library.
Author-email: 2AM mimo! <fearmimo2012@gmail.com>
Project-URL: Homepage, https://github.com/Archit-web-29/archit_ug
Project-URL: Source, https://github.com/Archit-web-29/archit_ug
Project-URL: Tracker, https://github.com/Archit-web-29/archit_ug/issues
Keywords: errol,sonic,LLM,cerebras,AI,chat,interactive
Requires-Python: >=3.8
License-File: LICENSE
Requires-Dist: cerebras-cloud-sdk
Requires-Dist: colorama
Dynamic: license-file
